{
  "id": "kanji-07d9a",
  "type": "kanji",
  "kanji": "続",
  "hex": "07d9a",
  "officialGrade": 4,
  "localGrade": 4,
  "officialSequence": 127,
  "status": "official-and-local",
  "strokeCount": 13,
  "meanings": [
    "continue",
    "sequel",
    "series"
  ],
  "readings": [
    {
      "id": "reading-9e5ea984a8676f17",
      "type": "kun",
      "reading": "つぐ.ない",
      "provenance": {
        "claims": [
          {
            "predicate": "kunReading",
            "value": "つぐ.ない",
            "sourceId": "kanjiapi-v1-local-info",
            "sourceUri": "https://kanjiapi.dev/v1/kanji/%E7%B6%9A",
            "confidence": 0.8,
            "capturedAt": "2026-04-24T04:23:49.197Z"
          }
        ],
        "sourceIds": [
          "kanjiapi-v1-local-info"
        ]
      }
    },
    {
      "id": "reading-f2cdda9d5356bdd7",
      "type": "kun",
      "reading": "つづ.く",
      "provenance": {
        "claims": [
          {
            "predicate": "kunReading",
            "value": "つづ.く",
            "sourceId": "kanjiapi-v1-local-info",
            "sourceUri": "https://kanjiapi.dev/v1/kanji/%E7%B6%9A",
            "confidence": 0.8,
            "capturedAt": "2026-04-24T04:23:49.197Z"
          }
        ],
        "sourceIds": [
          "kanjiapi-v1-local-info"
        ]
      }
    },
    {
      "id": "reading-83d6608c82fbc75d",
      "type": "kun",
      "reading": "つづ.ける",
      "provenance": {
        "claims": [
          {
            "predicate": "kunReading",
            "value": "つづ.ける",
            "sourceId": "kanjiapi-v1-local-info",
            "sourceUri": "https://kanjiapi.dev/v1/kanji/%E7%B6%9A",
            "confidence": 0.8,
            "capturedAt": "2026-04-24T04:23:49.197Z"
          }
        ],
        "sourceIds": [
          "kanjiapi-v1-local-info"
        ]
      }
    },
    {
      "id": "reading-2c0e99e9e4229cce",
      "type": "on",
      "reading": "キョウ",
      "provenance": {
        "claims": [
          {
            "predicate": "onReading",
            "value": "キョウ",
            "sourceId": "kanjiapi-v1-local-info",
            "sourceUri": "https://kanjiapi.dev/v1/kanji/%E7%B6%9A",
            "confidence": 0.8,
            "capturedAt": "2026-04-24T04:23:49.197Z"
          }
        ],
        "sourceIds": [
          "kanjiapi-v1-local-info"
        ]
      }
    },
    {
      "id": "reading-2bca43f7bf8535a7",
      "type": "on",
      "reading": "コウ",
      "provenance": {
        "claims": [
          {
            "predicate": "onReading",
            "value": "コウ",
            "sourceId": "kanjiapi-v1-local-info",
            "sourceUri": "https://kanjiapi.dev/v1/kanji/%E7%B6%9A",
            "confidence": 0.8,
            "capturedAt": "2026-04-24T04:23:49.197Z"
          }
        ],
        "sourceIds": [
          "kanjiapi-v1-local-info"
        ]
      }
    },
    {
      "id": "reading-6f3a1a53352cfb1a",
      "type": "on",
      "reading": "ショク",
      "provenance": {
        "claims": [
          {
            "predicate": "onReading",
            "value": "ショク",
            "sourceId": "kanjiapi-v1-local-info",
            "sourceUri": "https://kanjiapi.dev/v1/kanji/%E7%B6%9A",
            "confidence": 0.8,
            "capturedAt": "2026-04-24T04:23:49.197Z"
          }
        ],
        "sourceIds": [
          "kanjiapi-v1-local-info"
        ]
      }
    },
    {
      "id": "reading-128bfa63a4643776",
      "type": "on",
      "reading": "ゾク",
      "provenance": {
        "claims": [
          {
            "predicate": "onReading",
            "value": "ゾク",
            "sourceId": "kanjiapi-v1-local-info",
            "sourceUri": "https://kanjiapi.dev/v1/kanji/%E7%B6%9A",
            "confidence": 0.8,
            "capturedAt": "2026-04-24T04:23:49.197Z"
          }
        ],
        "sourceIds": [
          "kanjiapi-v1-local-info"
        ]
      }
    }
  ],
  "vocab": [
    "vocab-7f619d23addc55a4",
    "vocab-2c2772e189beb458",
    "vocab-34b5bdcb458ba2ba",
    "vocab-ec10b2208d3d5105",
    "vocab-c364dca2834a8f26",
    "vocab-c684440e0b2eb43f",
    "vocab-7a0ebe02a97d320a",
    "vocab-7565a8231216175f"
  ],
  "progressions": [
    {
      "profileId": "grade-only",
      "grade": 4,
      "sequence": 127,
      "source_uri": "https://w3id.org/jp-cos/8210040141270000",
      "confidence": 1
    }
  ],
  "provenance": {
    "claims": [
      {
        "predicate": "officialCurriculumDocument",
        "value": "小学校学習指導要領（平成29年告示）",
        "sourceId": "mext-elementary-course-of-study-2017-pdf",
        "sourceUri": "https://www.mext.go.jp/component/a_menu/education/micro_detail/__icsFiles/afieldfile/2019/09/26/1413522_001.pdf",
        "confidence": 1,
        "capturedAt": "2026-04-24T04:23:49.197Z"
      },
      {
        "predicate": "officialGrade",
        "value": 4,
        "sourceId": "mext-cos-2017-grade-4-kanji",
        "sourceUri": "https://w3id.org/jp-cos/8210040141270000",
        "confidence": 1,
        "capturedAt": "2026-04-24T04:23:49.197Z"
      },
      {
        "predicate": "officialSequence",
        "value": 127,
        "sourceId": "mext-cos-2017-grade-4-kanji",
        "sourceUri": "https://w3id.org/jp-cos/8210040141270000",
        "confidence": 1,
        "capturedAt": "2026-04-24T04:23:49.197Z"
      },
      {
        "predicate": "localGrade",
        "value": 4,
        "sourceId": "kanjiapi-v1-local-grade",
        "sourceUri": "public/data/v1/grades/grade-4.json",
        "confidence": 0.8,
        "capturedAt": "2026-04-24T04:23:49.197Z"
      },
      {
        "predicate": "strokeCount",
        "value": 13,
        "sourceId": "kanjiapi-v1-local-info",
        "sourceUri": "https://kanjiapi.dev/v1/kanji/%E7%B6%9A",
        "confidence": 0.8,
        "capturedAt": "2026-04-24T04:23:49.197Z"
      },
      {
        "predicate": "strokeOrderSvg",
        "value": "07d9a.svg",
        "sourceId": "kanjivg-local-svg",
        "sourceUri": "public/data/v1/svg/07d9a.svg",
        "confidence": 0.8,
        "capturedAt": "2026-04-24T04:23:49.197Z"
      }
    ],
    "sourceIds": [
      "mext-elementary-course-of-study-2017-pdf",
      "mext-cos-2017-grade-4-kanji",
      "kanjiapi-v1-local-grade",
      "kanjiapi-v1-local-info",
      "kanjivg-local-svg"
    ]
  }
}
